{"name":"Ncheck","tagline":"Object checking library used for state based testing","body":"NCheck\r\n======\r\n\r\nLibrary providing object checking features primarily used for state based testing.\r\n\r\nAvailable as a NuGet package [NCheck](https://www.nuget.org/packages/NCheck/)\r\n\r\nWelcome to contributions from anyone.\r\n\r\nYou can see the version history [here](RELEASE_NOTES.md).\r\n\r\n## Library License\r\n\r\nThe library is available under the [MIT License](http://en.wikipedia.org/wiki/MIT_License), for more information see the [License file][1] in the GitHub repository.\r\n\r\n [1]: https://github.com/phatcher/NCheck/License.md\r\n","google":"","note":"Don't delete this file! It's used internally to help with page regeneration."}